sound_soup/__init__.py
sound_soup/core.py
sound_soup/exceptions.py
sound_soup/models.py
sound_soup-0.1.3.dist-info/licenses/LICENSE
sound_soup-0.1.3.dist-info/METADATA
sound_soup-0.1.3.dist-info/WHEEL
sound_soup-0.1.3.dist-info/top_level.txt
sound_soup-0.1.3.dist-info/RECORD
