Metadata-Version: 2.4
Name: sound-soup
Version: 0.1.3
Summary: BeautifulSoup-style API for audio transcription and analysis
Author-email: PierrunoYT <pierrebruno@hotmail.ch>
License-Expression: MIT
Project-URL: Homepage, https://github.com/PierrunoYT/sound-soup
Project-URL: Documentation, https://github.com/PierrunoYT/sound-soup#readme
Project-URL: Repository, https://github.com/PierrunoYT/sound-soup
Project-URL: Bug Tracker, https://github.com/PierrunoYT/sound-soup/issues
Keywords: audio,transcription,whisper,youtube,podcast
Classifier: Development Status :: 3 - Alpha
Classifier: Intended Audience :: Developers
Classifier: Topic :: Multimedia :: Sound/Audio :: Analysis
Classifier: Programming Language :: Python :: 3.9
Classifier: Programming Language :: Python :: 3.10
Classifier: Programming Language :: Python :: 3.11
Classifier: Programming Language :: Python :: 3.12
Requires-Python: >=3.9
License-File: LICENSE
Requires-Dist: openai-whisper>=20231117
Requires-Dist: yt-dlp>=2023.12.30
Requires-Dist: pydub>=0.25.1
Provides-Extra: dev
Requires-Dist: pytest>=7.0; extra == "dev"
Requires-Dist: black>=23.0; extra == "dev"
Requires-Dist: ruff>=0.1.0; extra == "dev"
Provides-Extra: fuzzy
Requires-Dist: thefuzz>=0.20.0; extra == "fuzzy"
Requires-Dist: python-Levenshtein>=0.21.0; extra == "fuzzy"
Dynamic: license-file
